bitemporal_timeseries-0.1.0.dist-info/METADATA
bitemporal_timeseries-0.1.0.dist-info/WHEEL
bitemporal_timeseries/__init__.py
bitemporal_timeseries/bitemporal_timeseries.cpython-312-x86_64-linux-gnu.so
bitemporal_timeseries/processor.py
bitemporal_timeseries-0.1.0.dist-info/RECORD
