Metadata-Version: 2.4
Name: bitemporal-timeseries
Version: 0.1.0
Requires-Dist: pyarrow>=14.0.0
Requires-Dist: pandas>=2.0.0
Requires-Dist: numpy>=1.24.0
Requires-Dist: arro3-core
Requires-Dist: pytest>=7.0 ; extra == 'dev'
Requires-Dist: pytest-benchmark ; extra == 'dev'
Requires-Dist: black ; extra == 'dev'
Requires-Dist: mypy ; extra == 'dev'
Requires-Dist: ruff ; extra == 'dev'
Provides-Extra: dev
Summary: High-performance bitemporal timeseries update processor
Requires-Python: >=3.8
